krakenapi/__init__.py
krakenapi/kraken_api.py
krakenapi/utils.py
tests/__init__.py
tests/conftest.py
tests/test_kraken_api.py
tests/test_utils.py
tests/fixtures/__init__.py
tests/fixtures/trades.py
krakenapi-1.0.2.dist-info/LICENSE
krakenapi-1.0.2.dist-info/METADATA
krakenapi-1.0.2.dist-info/WHEEL
krakenapi-1.0.2.dist-info/top_level.txt
krakenapi-1.0.2.dist-info/zip-safe
krakenapi-1.0.2.dist-info/RECORD
